my_service_manager/__init__.py
my_service_manager/manager.py
my_service_manager-1.0.7.dist-info/METADATA
my_service_manager-1.0.7.dist-info/WHEEL
my_service_manager-1.0.7.dist-info/top_level.txt
my_service_manager-1.0.7.dist-info/RECORD
